deepset_cloud_sdk/README.md
deepset_cloud_sdk/__init__.py
deepset_cloud_sdk/_api/config.py
deepset_cloud_sdk/_api/deepset_cloud_api.py
deepset_cloud_sdk/_api/files.py
deepset_cloud_sdk/_api/upload_sessions.py
deepset_cloud_sdk/_s3/__init__.py
deepset_cloud_sdk/_s3/upload.py
deepset_cloud_sdk/_service/files_service.py
deepset_cloud_sdk/_service/pipeline_service.py
deepset_cloud_sdk/_utils/__init__.py
deepset_cloud_sdk/_utils/datetime.py
deepset_cloud_sdk/cli.py
deepset_cloud_sdk/models.py
deepset_cloud_sdk/workflows/__init__.py
deepset_cloud_sdk/workflows/async_client/__init__.py
deepset_cloud_sdk/workflows/async_client/async_pipeline_client.py
deepset_cloud_sdk/workflows/async_client/files.py
deepset_cloud_sdk/workflows/sync_client/__init__.py
deepset_cloud_sdk/workflows/sync_client/files.py
deepset_cloud_sdk/workflows/sync_client/pipeline_client.py
deepset_cloud_sdk/workflows/sync_client/utils.py
deepset_cloud_sdk-1.7.3.dist-info/WHEEL
deepset_cloud_sdk-1.7.3.dist-info/entry_points.txt
deepset_cloud_sdk-1.7.3.dist-info/METADATA
deepset_cloud_sdk-1.7.3.dist-info/RECORD
