Metadata-Version: 2.4
Name: deepset-cloud-sdk
Version: 1.7.3
Summary: deepset SDK
Keywords: 
Author: deepset
Author-email: deepset <rohan.janjua@deepset.ai>
License-Expression: Apache-2.0
Classifier: Development Status :: 4 - Beta
Classifier: Programming Language :: Python
Classifier: Programming Language :: Python :: 3.8
Classifier: Programming Language :: Python :: 3.9
Classifier: Programming Language :: Python :: 3.10
Classifier: Programming Language :: Python :: 3.11
Classifier: Programming Language :: Python :: Implementation :: CPython
Classifier: Programming Language :: Python :: Implementation :: PyPy
Requires-Dist: structlog>=24.0.0
Requires-Dist: httpx>=0.27.2
Requires-Dist: python-dotenv>=1.0.1
Requires-Dist: typer>=0.15.0
Requires-Dist: click<=8.2.0
Requires-Dist: tenacity>=8.3.0
Requires-Dist: aiohttp>=3.10.10
Requires-Dist: aiofiles>=24.1.0
Requires-Dist: tabulate>=0.9.0
Requires-Dist: tqdm>=4.66.4
Requires-Dist: yaspin>=3.0.0
Requires-Dist: pyrate-limiter>=3.7.0
Requires-Dist: pydantic>=2.11.4
Requires-Dist: ruamel-yaml>=0.18.10
Requires-Python: >=3.9
Project-URL: Documentation, https://github.com/deepset-ai/deepset-cloud-sdk#readme
Project-URL: Issues, https://github.com/deepset-ai/deepset-cloud-sdk/issues
Project-URL: Source, https://github.com/deepset-ai/deepset-cloud-sdk
